fivetran/__init__.py
fivetran/certificate_management.py
fivetran/connector_management.py
fivetran/connector_schema_management.py
fivetran/dbt_transformation_management.py
fivetran/destination_management.py
fivetran/group_management.py
fivetran/metadata_management.py
fivetran/role_management.py
fivetran/sdk.py
fivetran/team_management.py
fivetran/user_management.py
fivetran/webhook_management.py
fivetran/models/__init__.py
fivetran/models/operations/__init__.py
fivetran/models/operations/add_team_membership_in_connector.py
fivetran/models/operations/add_team_membership_in_group.py
fivetran/models/operations/add_user_membership_in_connector.py
fivetran/models/operations/add_user_membership_in_group.py
fivetran/models/operations/add_user_to_group.py
fivetran/models/operations/add_user_to_team.py
fivetran/models/operations/approve_certificate.py
fivetran/models/operations/approve_fingerprint.py
fivetran/models/operations/column_metadata.py
fivetran/models/operations/connect_card.py
fivetran/models/operations/connector_column_config.py
fivetran/models/operations/connector_details.py
fivetran/models/operations/connector_schema_config.py
fivetran/models/operations/create_account_webhook.py
fivetran/models/operations/create_connector.py
fivetran/models/operations/create_dbt_project.py
fivetran/models/operations/create_dbt_transformation.py
fivetran/models/operations/create_destination.py
fivetran/models/operations/create_group.py
fivetran/models/operations/create_group_webhook.py
fivetran/models/operations/create_team.py
fivetran/models/operations/create_user.py
fivetran/models/operations/dbt_model_details.py
fivetran/models/operations/dbt_project_details.py
fivetran/models/operations/dbt_transformation_details.py
fivetran/models/operations/delete_connector.py
fivetran/models/operations/delete_dbt_transformation.py
fivetran/models/operations/delete_destination.py
fivetran/models/operations/delete_group.py
fivetran/models/operations/delete_team.py
fivetran_python_sdk-1.7.0.dist-info/LICENSE.md
fivetran_python_sdk-1.7.0.dist-info/METADATA
fivetran_python_sdk-1.7.0.dist-info/WHEEL
fivetran_python_sdk-1.7.0.dist-info/top_level.txt
fivetran_python_sdk-1.7.0.dist-info/RECORD
