Metadata-Version: 2.1
Name: fivetran-python-sdk
Version: 1.7.0
Summary: Python SDK for Fivetran API
Home-page: UNKNOWN
Author: speakeasy-sdks
License: UNKNOWN
Platform: UNKNOWN
Requires-Python: >=3.9
License-File: LICENSE.md
Requires-Dist: certifi (==2022.12.07)
Requires-Dist: charset-normalizer (==2.1.1)
Requires-Dist: dataclasses-json-speakeasy (==0.5.8)
Requires-Dist: idna (==3.3)
Requires-Dist: marshmallow (==3.17.1)
Requires-Dist: marshmallow-enum (==1.5.1)
Requires-Dist: mypy-extensions (==0.4.3)
Requires-Dist: packaging (==21.3)
Requires-Dist: pyparsing (==3.0.9)
Requires-Dist: python-dateutil (==2.8.2)
Requires-Dist: requests (==2.28.1)
Requires-Dist: six (==1.16.0)
Requires-Dist: typing-inspect (==0.8.0)
Requires-Dist: typing-extensions (==4.3.0)
Requires-Dist: urllib3 (==1.26.12)
Requires-Dist: pylint (==2.16.2)
